toansttlib/GenerateDataset.py
toansttlib/TCSVResult.py
toansttlib/TChart.py
toansttlib/TChart_example.py
toansttlib/TTable.py
toansttlib/__init__.py
toansttlib-2.11.0.dist-info/LICENSE
toansttlib-2.11.0.dist-info/METADATA
toansttlib-2.11.0.dist-info/WHEEL
toansttlib-2.11.0.dist-info/top_level.txt
toansttlib-2.11.0.dist-info/RECORD
