Metadata-Version: 2.1
Name: toansttlib
Version: 2.11.0
Summary: A tool package
Home-page: https://github.com/
Author: toanstt
Author-email: toanstt@yahoo.com
Classifier: Programming Language :: Python :: 3
Classifier: License :: OSI Approved :: MIT License
Classifier: Operating System :: OS Independent
Requires-Python: >=3.6
License-File: LICENSE
